s1300180_learn/__init__.py
s1300180_learn/statistics/__init__.py
s1300180_learn/statistics/frequenciesOfItems.py
s1300180_learn/visualization/__init__.py
s1300180_learn/visualization/heatMapItemsFrequencies.py
s1300180_learn-2024.7.29.dist-info/METADATA
s1300180_learn-2024.7.29.dist-info/WHEEL
s1300180_learn-2024.7.29.dist-info/top_level.txt
s1300180_learn-2024.7.29.dist-info/RECORD
